setup.py
pyprofqueue/__init__.py
pyprofqueue/script.py
pyprofqueue/submission.py
pyprofqueue/utils.py
pyprofqueue.egg-info/PKG-INFO
pyprofqueue.egg-info/SOURCES.txt
pyprofqueue.egg-info/dependency_links.txt
pyprofqueue.egg-info/requires.txt
pyprofqueue.egg-info/top_level.txt
pyprofqueue/../ReadMe.md
pyprofqueue/batch_systems/pbs.py
pyprofqueue/batch_systems/slurm.py
pyprofqueue/profilers/likwid.py
pyprofqueue/profilers/linaro_forge.py
pyprofqueue/profilers/prometheus.py
pyprofqueue/profilers/data/_template_commands.txt
pyprofqueue/profilers/data/likwid_commands.txt
pyprofqueue/profilers/data/linaro_forge_commands.txt
pyprofqueue/profilers/data/prometheus_commands.txt
pyprofqueue/profilers/data/read_prometheus.py