Metadata-Version: 2.1
Name: pyprofqueue
Version: 0.4.0
Summary: pyprofqueue serves as a python package that can take in existing bash scripts, add initialisations and calls to use profilers on the bash script, and submit the script to an HPC queue system on the users' behalf.
Home-page: https://github.com/uksrc-developers/PyProfQueue
Author: Marcus Keil
Author-email: marcusk050291@gmail.com
License: MIT License
Classifier: Development Status :: 3 - Alpha
Classifier: Intended Audience :: Science/Research
Classifier: License :: OSI Approved :: BSD License
Classifier: Operating System :: POSIX :: Linux
Classifier: Programming Language :: Python :: 3.10
Requires-Dist: pytz
Requires-Dist: h5py
Requires-Dist: numpy
Requires-Dist: tables
Requires-Dist: pyarrow
Requires-Dist: matplotlib
Requires-Dist: pandas<=2.2.1
Requires-Dist: promql_http_api==0.3.3
